ads2bibdesk/__init__.py
ads2bibdesk/ads2bibdesk.cfg.default
ads2bibdesk/ads2bibdesk.py
ads2bibdesk/bibdesk.py
ads2bibdesk/prefs.py
ads2bibdesk-0.2.dev3.dist-info/LICENSE
ads2bibdesk-0.2.dev3.dist-info/METADATA
ads2bibdesk-0.2.dev3.dist-info/WHEEL
ads2bibdesk-0.2.dev3.dist-info/entry_points.txt
ads2bibdesk-0.2.dev3.dist-info/top_level.txt
ads2bibdesk-0.2.dev3.dist-info/RECORD
