Metadata-Version: 2.1
Name: ads2bibdesk
Version: 0.2.dev3
Summary: Add articles from the new NASA/SAO ADS to your BibDeskbibliography (based on ads_bibdesk from J. Sick et al.).
Home-page: https://github.com/r-xue/ads2bibdesk
Author: Rui Xue
License: UNKNOWN
Project-URL: Bug Reports, https://github.com/r-xue/ads2bibdesk/issues
Project-URL: Source, https://github.com/r-xue/ads2bibdesk/
Keywords: bibtex astronomy ADS
Platform: UNKNOWN
Classifier: Development Status :: 4 - Beta
Classifier: Programming Language :: Python :: 3
Classifier: Programming Language :: Python :: 3.6
Classifier: Programming Language :: Python :: 3.7
Classifier: Programming Language :: Python :: 3.8
Classifier: Intended Audience :: Science/Research
Classifier: License :: OSI Approved :: GNU General Public License v3 (GPLv3)
Classifier: Operating System :: MacOS :: MacOS X
Classifier: Topic :: Scientific/Engineering :: Astronomy
Requires-Python: >=3.6, <4
Requires-Dist: ads
Requires-Dist: requests
Requires-Dist: lxml
Requires-Dist: pyobjc-framework-Cocoa
